restify/RuminatingCogitation.py
restify/__init__.py
restify/__main__.py
restify/main.py
restify_ENGYAK-0.2.11.dist-info/LICENSE
restify_ENGYAK-0.2.11.dist-info/METADATA
restify_ENGYAK-0.2.11.dist-info/WHEEL
restify_ENGYAK-0.2.11.dist-info/top_level.txt
restify_ENGYAK-0.2.11.dist-info/RECORD
