Metadata-Version: 2.1
Name: restify-ENGYAK
Version: 0.2.11
Summary: Abstractions should save typing, not thinking! This project will provide a quick and simple CLI for REST API consumption. Build your own library of known API endpoints/modifiers, and consume directly via the CLI.
Home-page: https://github.com/ngschmidt/python-resttool
Author: Nicholas Schmidt
Author-email: nick.schmidt3@gmail.com
Classifier: Programming Language :: Python :: 3
Classifier: License :: OSI Approved :: GNU General Public License v3 (GPLv3)
Classifier: Operating System :: OS Independent
Requires-Python: >=3.6
License-File: LICENSE
